django_redis_monitor/__init__.py
django_redis_monitor/admin.py
django_redis_monitor/apps.py
django_redis_monitor/models.py
django_redis_monitor/signals.py
django_redis_monitor/snapshot.py
django_redis_monitor/tests.py
django_redis_monitor/views.py
django_redis_monitor/migrations/0001_initial.py
django_redis_monitor/migrations/0002_remove_monitoredkey_enable_snapshot_and_more.py
django_redis_monitor/migrations/0003_alter_keysnapshottask_last_status.py
django_redis_monitor/migrations/__init__.py
django_redis_monitor/static/admin/js/metrics_chart.js
django_redis_monitor-0.1.2.dist-info/licenses/LICENSE
django_redis_monitor-0.1.2.dist-info/METADATA
django_redis_monitor-0.1.2.dist-info/WHEEL
django_redis_monitor-0.1.2.dist-info/top_level.txt
django_redis_monitor-0.1.2.dist-info/RECORD
