Metadata-Version: 2.4
Name: django-redis-monitor
Version: 0.1.2
Summary: 轻量的 Django 应用，用于监控 Redis 键并按任务周期采集快照。
Author: Cone387
License-Expression: MIT
Classifier: Framework :: Django
Classifier: Programming Language :: Python :: 3
Classifier: Programming Language :: Python :: 3 :: Only
Classifier: Operating System :: OS Independent
Requires-Python: >=3.13
License-File: LICENSE
Requires-Dist: django>=5.2.6
Requires-Dist: django-sched>=0.1.3
Requires-Dist: redis>=6.4.0
Dynamic: license-file
